semester-modules/Ex10/PWM11.sv
module PWM11(
    input logic clk,
    input logic rst_n,
    input logic [10:0] duty,
    output logic pwm1,
    output logic pwm2,
    output logic PWM_synch,
    output logic ovr_I_blank
);

    localparam int NONOVERLAP = 11'h040; // Buffer ensuring PWM1 and PWM2 are never both high (would result in short)
    logic [10:0] cnt;
    logic pwm1_set, pwm1_rst, pwm2_set, pwm2_rst;

    // counter ff
    always_ff @(posedge clk, negedge rst_n) begin
        if (rst_n)
            cnt <= 11'h000;
        else if (cnt != 11'h7FF)
            cnt <= cnt + 1;
        else
            cnt <= 0;
    end

    // set/reset comb logic
    always_comb begin
        pwm1_set = (cnt >= (duty + NONOVERLAP)); // PWM1 is high from NONOVERLAP to duty
        pwm1_rst = &cnt;
        pwm2_set = (cnt >= (NONOVERLAP));        // PWM2 is high from duty + NONOVERLAP to 2047
        pwm2_rst = (cnt >= duty);
    end

    // PWM 1 ff
    always_ff @(posedge clk, negedge rst_n) begin
        if (rst_n)
            pwm1 <= 1'b0;
        else if (pwm1_set)
            pwm1 <= 1'b1;
        else if (pwm1_rst)
            pwm1 <= 1'b0;
    end

    // PWM 2 ff
    always_ff @(posedge clk, negedge rst_n) begin
        if (rst_n)
            pwm2 <= 1'b0;
        else if (pwm2_set)
            pwm2 <= 1'b1;
        else if (pwm2_rst)
            pwm2 <= 1'b0;
    end

    // Additional comb logic 
    always_comb begin

        PWM_synch = ~|cnt; // Will be used in the future to ensure duty doesn't change in the middle of PWM cycle

        // If the current is too high, another module can use this signal to shutdown the circuit
        ovr_I_blank = (NONOVERLAP < cnt < (NONOVERLAP + 128)) || ((NONOVERLAP + duty) < cnt < (NONOVERLAP + duty + 128));

    end

endmodule

semester-modules/Ex11/PWM11_tb.sv
module PWM11_tb;

    // DUT signals
    logic clk;
    logic rst_n;
    logic [10:0] duty;
    logic pwm1;
    logic pwm2;
    wire PWM_synch;
    wire ovr_I_blank;

    PWM11 dut (
        .clk(clk),
        .rst_n(rst_n),
        .duty(duty),
        .pwm1(pwm1),
        .pwm2(pwm2),
        .PWM_synch(PWM_synch),
        .ovr_I_blank(ovr_I_blank)
    );

    initial clk = 1'b0;
    always #5 clk = ~clk;

    // Monitor for console output
    initial begin
        $display("time\tduty\tpwm1\tpwm2\tPWM_synch\tovr_I_blank");
        $monitor("%0t\t%0h\t%b\t%b\t%b\t%b", $time, duty, pwm1, pwm2, PWM_synch, ovr_I_blank);
    end

    always @(posedge clk) begin
        if (pwm1 && pwm2) begin
            $display("[%0t] ERROR: pwm1 and pwm2 are both high!", $time);
            $stop();
        end
    end

    initial begin

        // Reset
        rst_n = 1'b0;
        duty = 11'h000;
        #20;
        rst_n = 1'b1;

        @(posedge PWM_synch);

        // Test values: 0, small, just below NONOVERLAP, equal NONOVERLAP, mid, max
        duty = 11'h000; // 0% (expect pwm1=0 pwm2 toggles)
        @(posedge PWM_synch); repeat (4) @(posedge PWM_synch);

        duty = 11'h020; // small duty
        @(posedge PWM_synch); repeat (4) @(posedge PWM_synch);

        duty = 11'h03F; // just below NONOVERLAP
        @(posedge PWM_synch); repeat (4) @(posedge PWM_synch);

        duty = 11'h040; // equal NONOVERLAP
        @(posedge PWM_synch); repeat (4) @(posedge PWM_synch);

        duty = 11'h200; // mid duty
        @(posedge PWM_synch); repeat (4) @(posedge PWM_synch);

        duty = 11'h7FF; // full-scale
        @(posedge PWM_synch); repeat (4) @(posedge PWM_synch);

        $display("Yahoo! The code simulated without breaking");
        #10 $stop();
        
    end

endmodule

semester-modules/Ex11/pwm11.vcd
$date
	Mon Oct 13 10:15:50 2025
$end
$version
	ModelSim Version 2020.1
$end
$timescale
	1ps
$end

$scope module PWM11_tb $end
$var reg 1 ! clk $end
$var reg 1 " rst_n $end
$var reg 11 # duty [10:0] $end
$var wire 1 $ pwm1 $end
$var wire 1 % pwm2 $end
$var wire 1 & PWM_synch $end
$var wire 1 ' ovr_I_blank $end

$scope module dut $end
$var parameter 1 ( NONOVERLAP $end
$var wire 1 ) clk $end
$var wire 1 * rst_n $end
$var wire 1 + duty [10] $end
$var wire 1 , duty [9] $end
$var wire 1 - duty [8] $end
$var wire 1 . duty [7] $end
$var wire 1 / duty [6] $end
$var wire 1 0 duty [5] $end
$var wire 1 1 duty [4] $end
$var wire 1 2 duty [3] $end
$var wire 1 3 duty [2] $end
$var wire 1 4 duty [1] $end
$var wire 1 5 duty [0] $end
$var reg 1 6 pwm1 $end
$var reg 1 7 pwm2 $end
$var reg 1 8 PWM_synch $end
$var reg 1 9 ovr_I_blank $end
$var reg 11 : cnt [10:0] $end
$var reg 1 ; pwm1_set $end
$var reg 1 < pwm1_rst $end
$var reg 1 = pwm2_set $end
$var reg 1 > pwm2_rst $end
$upscope $end
$upscope $end
$enddefinitions $end
#0
$dumpvars
0!
0"
b0 #
06
07
18
09
b0 :
1;
0<
1=
1>
b0 (
0$
0%
1&
0'
0)
0*
05
04
03
02
01
00
0/
0.
0-
0,
0+
$end
#5
1!
1)
#10
0!
0)
#15
1!
1)
#20
1"
0!
1*
0)
#25
1!
1)
b1 :
16
17
1$
1%
08
19
1'
0&
#30
0!
0)
#35
1!
1)
b10 :
#40
0!
0)
#45
1!
1)
b11 :
#50
0!
0)
#55
1!
1)
b100 :
#60
0!
0)
#65
1!
1)
b101 :
#70
0!
0)
#75
1!
1)
b110 :
#80
0!
0)
#85
1!
1)
b111 :
#90
0!
0)
#95
1!
1)
b1000 :
#100
0!
0)
#105
1!
1)
b1001 :
#110
0!
0)
#115
1!
1)
b1010 :
#120
0!
0)
#125
1!
1)
b1011 :
#130
0!
0)
#135
1!
1)
b1100 :
#140
0!
0)
#145
1!
1)
b1101 :
#150
0!
0)
#155
1!
1)
b1110 :
#160
0!
0)
#165
1!
1)
b1111 :
#170
0!
0)
#175
1!
1)
b10000 :
#180
0!
0)
#185
1!
1)
b10001 :
#190
0!
0)
#195
1!
1)
b10010 :
#200
0!
0)
#205
1!
1)
b10011 :
#210
0!
0)
#215
1!
1)
b10100 :
#220
0!
0)
#225
1!
1)
b10101 :
#230
0!
0)
#235
1!
1)
b10110 :
#240
0!
0)
#245
1!
1)
b10111 :
#250
0!
0)
#255
1!
1)
b11000 :
#260
0!
0)
#265
1!
1)
b11001 :
#270
0!
0)
#275
1!
1)
b11010 :
#280
0!
0)
#285
1!
1)
b11011 :
#290
0!
0)
#295
1!
1)
b11100 :
#300
0!
0)
#305
1!
1)
b11101 :
#310
0!
0)
#315
1!
1)
b11110 :
#320
0!
0)
#325
1!
1)
b11111 :
#330
0!
0)
#335
1!
1)
b100000 :
#340
0!
0)
#345
1!
1)
b100001 :
#350
0!
0)
#355
1!
1)
b100010 :
#360
0!
0)
#365
1!
1)
b100011 :
#370
0!
0)
#375
1!
1)
b100100 :
#380
0!
0)
#385
1!
1)
b100101 :
#390
0!
0)
#395
1!
1)
b100110 :
#400
0!
0)
#405
1!
1)
b100111 :
#410
0!
0)
#415
1!
1)
b101000 :
#420
0!
0)
#425
1!
1)
b101001 :
#430
0!
0)
#435
1!
1)
b101010 :
#440
0!
0)
#445
1!
1)
b101011 :
#450
0!
0)
#455
1!
1)
b101100 :
#460
0!
0)
#465
1!
1)
b101101 :
#470
0!
0)
#475
1!
1)
b101110 :
#480
0!
0)
#485
1!
1)
b101111 :
#490
0!
0)
#495
1!
1)
b110000 :
#500
0!
0)
#505
1!
1)
b110001 :
#510
0!
0)
#515
1!
1)
b110010 :
#520
0!
0)
#525
1!
1)
b110011 :
#530
0!
0)
#535
1!
1)
b110100 :
#540
0!
0)
#545
1!
1)
b110101 :
#550
0!
0)
#555
1!
1)
b110110 :
#560
0!
0)
#565
1!
1)
b110111 :
#570
0!
0)
#575
1!
1)
b111000 :
#580
0!
0)
#585
1!
1)
b111001 :
#590
0!
0)
#595
1!
1)
b111010 :
#600
0!
0)
#605
1!
1)
b111011 :
#610
0!
0)
#615
1!
1)
b111100 :
#620
0!
0)
#625
1!
1)
b111101 :
#630
0!
0)
#635
1!
1)
b111110 :
#640
0!
0)
#645
1!
1)
b111111 :
#650
0!
0)
#655
1!
1)
b1000000 :
#660
0!
0)
#665
1!
1)
b1000001 :
#670
0!
0)
#675
1!
1)
b1000010 :
#680
0!
0)
#685
1!
1)
b1000011 :
#690
0!
0)
#695
1!
1)
b1000100 :
#700
0!
0)
#705
1!
1)
b1000101 :
#710
0!
0)
#715
1!
1)
b1000110 :
#720
0!
0)
#725
1!
1)
b1000111 :
#730
0!
0)
#735
1!
1)
b1001000 :
#740
0!
0)
#745
1!
1)
b1001001 :
#750
0!
0)
#755
1!
1)
b1001010 :
#760
0!
0)
#765
1!
1)
b1001011 :
#770
0!
0)
#775
1!
1)
b1001100 :
#780
0!
0)
#785
1!
1)
b1001101 :
#790
0!
0)
#795
1!
1)
b1001110 :
#800
0!
0)
#805
1!
1)
b1001111 :
#810
0!
0)
#815
1!
1)
b1010000 :
#820
0!
0)
#825
1!
1)
b1010001 :
#830
0!
0)
#835
1!
1)
b1010010 :
#840
0!
0)
#845
1!
1)
b1010011 :
#850
0!
0)
#855
1!
1)
b1010100 :
#860
0!
0)
#865
1!
1)
b1010101 :
#870
0!
0)
#875
1!
1)
b1010110 :
#880
0!
0)
#885
1!
1)
b1010111 :
#890
0!
0)
#895
1!
1)
b1011000 :
#900
0!
0)
#905
1!
1)
b1011001 :
#910
0!
0)
#915
1!
1)
b1011010 :
#920
0!
0)
#925
1!
1)
b1011011 :
#930
0!
0)
#935
1!
1)
b1011100 :
#940
0!
0)
#945
1!
1)
b1011101 :
#950
0!
0)
#955
1!
1)
b1011110 :
#960
0!
0)
#965
1!
1)
b1011111 :
#970
0!
0)
#975
1!
1)
b1100000 :
#980
0!
0)
#985
1!
1)
b1100001 :
#990
0!
0)
#995
1!
1)
b1100010 :
#1000
0!
0)
#1005
1!
1)
b1100011 :
#1010
0!
0)
#1015
1!
1)
b1100100 :
#1020
0!
0)
#1025
1!
1)
b1100101 :
#1030
0!
0)
#1035
1!
1)
b1100110 :
#1040
0!
0)
#1045
1!
1)
b1100111 :
#1050
0!
0)
#1055
1!
1)
b1101000 :
#1060
0!
0)
#1065
1!
1)
b1101001 :
#1070
0!
0)
#1075
1!
1)
b1101010 :
#1080
0!
0)
#1085
1!
1)
b1101011 :
#1090
0!
0)
#1095
1!
1)
b1101100 :
#1100
0!
0)
#1105
1!
1)
b1101101 :
#1110
0!
0)
#1115
1!
1)
b1101110 :
#1120
0!
0)
#1125
1!
1)
b1101111 :
#1130
0!
0)
#1135
1!
1)
b1110000 :
#1140
0!
0)
#1145
1!
1)
b1110001 :
#1150
0!
0)
#1155
1!
1)
b1110010 :
#1160
0!
0)
#1165
1!
1)
b1110011 :
#1170
0!
0)
#1175
1!
1)
b1110100 :
#1180
0!
0)
#1185
1!
1)
b1110101 :
#1190
0!
0)
#1195
1!
1)
b1110110 :
#1200
0!
0)
#1205
1!
1)
b1110111 :
#1210
0!
0)
#1215
1!
1)
b1111000 :
#1220
0!
0)
#1225
1!
1)
b1111001 :
#1230
0!
0)
#1235
1!
1)
b1111010 :
#1240
0!
0)
#1245
1!
1)
b1111011 :
#1250
0!
0)
#1255
1!
1)
b1111100 :
#1260
0!
0)
#1265
1!
1)
b1111101 :
#1270
0!
0)
#1275
1!
1)
b1111110 :
#1280
0!
0)
#1285
1!
1)
b1111111 :
#1290
0!
0)
#1295
1!
1)
b10000000 :
09
0'
#1300
0!
0)
#1305
1!
1)
b10000001 :
#1310
0!
0)
#1315
1!
1)
b10000010 :
#1320
0!
0)
#1325
1!
1)
b10000011 :
#1330
0!
0)
#1335
1!
1)
b10000100 :
#1340
0!
0)
#1345
1!
1)
b10000101 :
#1350
0!
0)
#1355
1!
1)
b10000110 :
#1360
0!
0)
#1365
1!
1)
b10000111 :
#1370
0!
0)
#1375
1!
1)
b10001000 :
#1380
0!
0)
#1385
1!
1)
b10001001 :
#1390
0!
0)
#1395
1!
1)
b10001010 :
#1400
0!
0)
#1405
1!
1)
b10001011 :
#1410
0!
0)
#1415
1!
1)
b10001100 :
#1420
0!
0)
#1425
1!
1)
b10001101 :
#1430
0!
0)
#1435
1!
1)
b10001110 :
#1440
0!
0)
#1445
1!
1)
b10001111 :
#1450
0!
0)
#1455
1!
1)
b10010000 :
#1460
0!
0)
#1465
1!
1)
b10010001 :
#1470
0!
0)
#1475
1!
1)
b10010010 :
#1480
0!
0)
#1485
1!
1)
b10010011 :
#1490
0!
0)
#1495
1!
1)
b10010100 :
#1500
0!
0)
#1505
1!
1)
b10010101 :
#1510
0!
0)
#1515
1!
1)
b10010110 :
#1520
0!
0)
#1525
1!
1)
b10010111 :
#1530
0!
0)
#1535
1!
1)
b10011000 :
#1540
0!
0)
#1545
1!
1)
b10011001 :
#1550
0!
0)
#1555
1!
1)
b10011010 :
#1560
0!
0)
#1565
1!
1)
b10011011 :
#1570
0!
0)
#1575
1!
1)
b10011100 :
#1580
0!
0)
#1585
1!
1)
b10011101 :
#1590
0!
0)
#1595
1!
1)
b10011110 :
#1600
0!
0)
#1605
1!
1)
b10011111 :
#1610
0!
0)
#1615
1!
1)
b10100000 :
#1620
0!
0)
#1625
1!
1)
b10100001 :
#1630
0!
0)
#1635
1!
1)
b10100010 :
#1640
0!
0)
#1645
1!
1)
b10100011 :
#1650
0!
0)
#1655
1!
1)
b10100100 :
#1660
0!
0)
#1665
1!
1)
b10100101 :
#1670
0!
0)
#1675
1!
1)
b10100110 :
#1680
0!
0)
#1685
1!
1)
b10100111 :
#1690
0!
0)
#1695
1!
1)
b10101000 :
#1700
0!
0)
#1705
1!
1)
b10101001 :
#1710
0!
0)
#1715
1!
1)
b10101010 :
#1720
0!
0)
#1725
1!
1)
b10101011 :
#1730
0!
0)
#1735
1!
1)
b10101100 :
#1740
0!
0)
#1745
1!
1)
b10101101 :
#1750
0!
0)
#1755
1!
1)
b10101110 :
#1760
0!
0)
#1765
1!
1)
b10101111 :
#1770
0!
0)
#1775
1!
1)
b10110000 :
#1780
0!
0)
#1785
1!
1)
b10110001 :
#1790
0!
0)
#1795
1!
1)
b10110010 :
#1800
0!
0)
#1805
1!
1)
b10110011 :
#1810
0!
0)
#1815
1!
1)
b10110100 :
#1820
0!
0)
#1825
1!
1)
b10110101 :
#1830
0!
0)
#1835
1!
1)
b10110110 :
#1840
0!
0)
#1845
1!
1)
b10110111 :
#1850
0!
0)
#1855
1!
1)
b10111000 :
#1860
0!
0)
#1865
1!
1)
b10111001 :
#1870
0!
0)
#1875
1!
1)
b10111010 :
#1880
0!
0)
#1885
1!
1)
b10111011 :
#1890
0!
0)
#1895
1!
1)
b10111100 :
#1900
0!
0)
#1905
1!
1)
b10111101 :
#1910
0!
0)
#1915
1!
1)
b10111110 :
#1920
0!
0)
#1925
1!
1)
b10111111 :
#1930
0!
0)
#1935
1!
1)
b11000000 :
#1940
0!
0)
#1945
1!
1)
b11000001 :
#1950
0!
0)
#1955
1!
1)
b11000010 :
#1960
0!
0)
#1965
1!
1)
b11000011 :
#1970
0!
0)
#1975
1!
1)
b11000100 :
#1980
0!
0)
#1985
1!
1)
b11000101 :
#1990
0!
0)
#1995
1!
1)
b11000110 :
#2000
0!
0)
#2005
1!
1)
b11000111 :
#2010
0!
0)
#2015
1!
1)
b11001000 :
#2020
0!
0)
#2025
1!
1)
b11001001 :
#2030
0!
0)
#2035
1!
1)
b11001010 :
#2040
0!
0)
#2045
1!
1)
b11001011 :
#2050
0!
0)
#2055
1!
1)
b11001100 :
#2060
0!
0)
#2065
1!
1)
b11001101 :
#2070
0!
0)
#2075
1!
1)
b11001110 :
#2080
0!
0)
#2085
1!
1)
b11001111 :
#2090
0!
0)
#2095
1!
1)
b11010000 :
#2100
0!
0)
#2105
1!
1)
b11010001 :
#2110
0!
0)
#2115
1!
1)
b11010010 :
#2120
0!
0)
#2125
1!
1)
b11010011 :
#2130
0!
0)
#2135
1!
1)
b11010100 :
#2140
0!
0)
#2145
1!
1)
b11010101 :
#2150
0!
0)
#2155
1!
1)
b11010110 :
#2160
0!
0)
#2165
1!
1)
b11010111 :
#2170
0!
0)
#2175
1!
1)
b11011000 :
#2180
0!
0)
#2185
1!
1)
b11011001 :
#2190
0!
0)
#2195
1!
1)
b11011010 :
#2200
0!
0)
#2205
1!
1)
b11011011 :
#2210
0!
0)
#2215
1!
1)
b11011100 :
#2220
0!
0)
#2225
1!
1)
b11011101 :
#2230
0!
0)
#2235
1!
1)
b11011110 :
#2240
0!
0)
#2245
1!
1)
b11011111 :
#2250
0!
0)
#2255
1!
1)
b11100000 :
#2260
0!
0)
#2265
1!
1)
b11100001 :
#2270
0!
0)
#2275
1!
1)
b11100010 :
#2280
0!
0)
#2285
1!
1)
b11100011 :
#2290
0!
0)
#2295
1!
1)
b11100100 :
#2300
0!
0)
#2305
1!
1)
b11100101 :
#2310
0!
0)
#2315
1!
1)
b11100110 :
#2320
0!
0)
#2325
1!
1)
b11100111 :
#2330
0!
0)
#2335
1!
1)
b11101000 :
#2340
0!
0)
#2345
1!
1)
b11101001 :
#2350
0!
0)
#2355
1!
1)
b11101010 :
#2360
0!
0)
#2365
1!
1)
b11101011 :
#2370
0!
0)
#2375
1!
1)
b11101100 :
#2380
0!
0)
#2385
1!
1)
b11101101 :
#2390
0!
0)
#2395
1!
1)
b11101110 :
#2400
0!
0)
#2405
1!
1)
b11101111 :
#2410
0!
0)
#2415
1!
1)
b11110000 :
#2420
0!
0)
#2425
1!
1)
b11110001 :
#2430
0!
0)
#2435
1!
1)
b11110010 :
#2440
0!
0)
#2445
1!
1)
b11110011 :
#2450
0!
0)
#2455
1!
1)
b11110100 :
#2460
0!
0)
#2465
1!
1)
b11110101 :
#2470
0!
0)
#2475
1!
1)
b11110110 :
#2480
0!
0)
#2485
1!
1)
b11110111 :
#2490
0!
0)
#2495
1!
1)
b11111000 :
#2500
0!
0)
#2505
1!
1)
b11111001 :
#2510
0!
0)
#2515
1!
1)
b11111010 :
#2520
0!
0)
#2525
1!
1)
b11111011 :
#2530
0!
0)
#2535
1!
1)
b11111100 :
#2540
0!
0)
#2545
1!
1)
b11111101 :
#2550
0!
0)
#2555
1!
1)
b11111110 :
#2560
0!
0)
#2565
1!
1)
b11111111 :
#2570
0!
0)
#2575
1!
1)
b100000000 :
#2580
0!
0)
#2585
1!
1)
b100000001 :
#2590
0!
0)
#2595
1!
1)
b100000010 :
#2600
0!
0)
#2605
1!
1)
b100000011 :
#2610
0!
0)
#2615
1!
1)
b100000100 :
#2620
0!
0)
#2625
1!
1)
b100000101 :
#2630
0!
0)
#2635
1!
1)
b100000110 :
#2640
0!
0)
#2645
1!
1)
b100000111 :
#2650
0!
0)
#2655
1!
1)
b100001000 :
#2660
0!
0)
#2665
1!
1)
b100001001 :
#2670
0!
0)
#2675
1!
1)
b100001010 :
#2680
0!
0)
#2685
1!
1)
b100001011 :
#2690
0!
0)
#2695
1!
1)
b100001100 :
#2700
0!
0)
#2705
1!
1)
b100001101 :
#2710
0!
0)
#2715
1!
1)
b100001110 :
#2720
0!
0)
#2725
1!
1)
b100001111 :
#2730
0!
0)
#2735
1!
1)
b100010000 :
#2740
0!
0)
#2745
1!
1)
b100010001 :
#2750
0!
0)
#2755
1!
1)
b100010010 :
#2760
0!
0)
#2765
1!
1)
b100010011 :
#2770
0!
0)
#2775
1!
1)
b100010100 :
#2780
0!
0)
#2785
1!
1)
b100010101 :
#2790
0!
0)
#2795
1!
1)
b100010110 :
#2800
0!
0)
#2805
1!
1)
b100010111 :
#2810
0!
0)
#2815
1!
1)
b100011000 :
#2820
0!
0)
#2825
1!
1)
b100011001 :
#2830
0!
0)
#2835
1!
1)
b100011010 :
#2840
0!
0)
#2845
1!
1)
b100011011 :
#2850
0!
0)
#2855
1!
1)
b100011100 :
#2860
0!
0)
#2865
1!
1)
b100011101 :
#2870
0!
0)
#2875
1!
1)
b100011110 :
#2880
0!
0)
#2885
1!
1)
b100011111 :
#2890
0!
0)
#2895
1!
1)
b100100000 :
#2900
0!
0)
#2905
1!
1)
b100100001 :
#2910
0!
0)
#2915
1!
1)
b100100010 :
#2920
0!
0)
#2925
1!
1)
b100100011 :
#2930
0!
0)
#2935
1!
1)
b100100100 :
#2940
0!
0)
#2945
1!
1)
b100100101 :
#2950
0!
0)
#2955
1!
1)
b100100110 :
#2960
0!
0)
#2965
1!
1)
b100100111 :
#2970
0!
0)
#2975
1!
1)
b100101000 :
#2980
0!
0)
#2985
1!
1)
b100101001 :
#2990
0!
0)
#2995
1!
1)
b100101010 :
#3000
0!
0)
#3005
1!
1)
b100101011 :
#3010
0!
0)
#3015
1!
1)
b100101100 :
#3020
0!
0)
#3025
1!
1)
b100101101 :
#3030
0!
0)
#3035
1!
1)
b100101110 :
#3040
0!
0)
#3045
1!
1)
b100101111 :
#3050
0!
0)
#3055
1!
1)
b100110000 :
#3060
0!
0)
#3065
1!
1)
b100110001 :
#3070
0!
0)
#3075
1!
1)
b100110010 :
#3080
0!
0)
#3085
1!
1)
b100110011 :
#3090
0!
0)
#3095
1!
1)
b100110100 :
#3100
0!
0)
#3105
1!
1)
b100110101 :
#3110
0!
0)
#3115
1!
1)
b100110110 :
#3120
0!
0)
#3125
1!
1)
b100110111 :
#3130
0!
0)
#3135
1!
1)
b100111000 :
#3140
0!
0)
#3145
1!
1)
b100111001 :
#3150
0!
0)
#3155
1!
1)
b100111010 :
#3160
0!
0)
#3165
1!
1)
b100111011 :
#3170
0!
0)
#3175
1!
1)
b100111100 :
#3180
0!
0)
#3185
1!
1)
b100111101 :
#3190
0!
0)
#3195
1!
1)
b100111110 :
#3200
0!
0)
#3205
1!
1)
b100111111 :
#3210
0!
0)
#3215
1!
1)
b101000000 :
#3220
0!
0)
#3225
1!
1)
b101000001 :
#3230
0!
0)
#3235
1!
1)
b101000010 :
#3240
0!
0)
#3245
1!
1)
b101000011 :
#3250
0!
0)
#3255
1!
1)
b101000100 :
#3260
0!
0)
#3265
1!
1)
b101000101 :
#3270
0!
0)
#3275
1!
1)
b101000110 :
#3280
0!
0)
#3285
1!
1)
b101000111 :
#3290
0!
0)
#3295
1!
1)
b101001000 :
#3300
0!
0)
#3305
1!
1)
b101001001 :
#3310
0!
0)
#3315
1!
1)
b101001010 :
#3320
0!
0)
#3325
1!
1)
b101001011 :
#3330
0!
0)
#3335
1!
1)
b101001100 :
#3340
0!
0)
#3345
1!
1)
b101001101 :
#3350
0!
0)
#3355
1!
1)
b101001110 :
#3360
0!
0)
#3365
1!
1)
b101001111 :
#3370
0!
0)
#3375
1!
1)
b101010000 :
#3380
0!
0)
#3385
1!
1)
b101010001 :
#3390
0!
0)
#3395
1!
1)
b101010010 :
#3400
0!
0)
#3405
1!
1)
b101010011 :
#3410
0!
0)
#3415
1!
1)
b101010100 :
#3420
0!
0)
#3425
1!
1)
b101010101 :
#3430
0!
0)
#3435
1!
1)
b101010110 :
#3440
0!
0)
#3445
1!
1)
b101010111 :
#3450
0!
0)
#3455
1!
1)
b101011000 :
#3460
0!
0)
#3465
1!
1)
b101011001 :
#3470
0!
0)
#3475
1!
1)
b101011010 :
#3480
0!
0)
#3485
1!
1)
b101011011 :
#3490
0!
0)
#3495
1!
1)
b101011100 :
#3500
0!
0)
#3505
1!
1)
b101011101 :
#3510
0!
0)
#3515
1!
1)
b101011110 :
#3520
0!
0)
#3525
1!
1)
b101011111 :
#3530
0!
0)
#3535
1!
1)
b101100000 :
#3540
0!
0)
#3545
1!
1)
b101100001 :
#3550
0!
0)
#3555
1!
1)
b101100010 :
#3560
0!
0)
#3565
1!
1)
b101100011 :
#3570
0!
0)
#3575
1!
1)
b101100100 :
#3580
0!
0)
#3585
1!
1)
b101100101 :
#3590
0!
0)
#3595
1!
1)
b101100110 :
#3600
0!
0)
#3605
1!
1)
b101100111 :
#3610
0!
0)
#3615
1!
1)
b101101000 :
#3620
0!
0)
#3625
1!
1)
b101101001 :
#3630
0!
0)
#3635
1!
1)
b101101010 :
#3640
0!
0)
#3645
1!
1)
b101101011 :
#3650
0!
0)
#3655
1!
1)
b101101100 :
#3660
0!
0)
#3665
1!
1)
b101101101 :
#3670
0!
0)
#3675
1!
1)
b101101110 :
#3680
0!
0)
#3685
1!
1)
b101101111 :
#3690
0!
0)
#3695
1!
1)
b101110000 :
#3700
0!
0)
#3705
1!
1)
b101110001 :
#3710
0!
0)
#3715
1!
1)
b101110010 :
#3720
0!
0)
#3725
1!
1)
b101110011 :
#3730
0!
0)
#3735
1!
1)
b101110100 :
#3740
0!
0)
#3745
1!
1)
b101110101 :
#3750
0!
0)
#3755
1!
1)
b101110110 :
#3760
0!
0)
#3765
1!
1)
b101110111 :
#3770
0!
0)
#3775
1!
1)
b101111000 :
#3780
0!
0)
#3785
1!
1)
b101111001 :
#3790
0!
0)
#3795
1!
1)
b101111010 :
#3800
0!
0)
#3805
1!
1)
b101111011 :
#3810
0!
0)
#3815
1!
1)
b101111100 :
#3820
0!
0)
#3825
1!
1)
b101111101 :
#3830
0!
0)
#3835
1!
1)
b101111110 :
#3840
0!
0)
#3845
1!
1)
b101111111 :
#3850
0!
0)
#3855
1!
1)
b110000000 :
#3860
0!
0)
#3865
1!
1)
b110000001 :
#3870
0!
0)
#3875
1!
1)
b110000010 :
#3880
0!
0)
#3885
1!
1)
b110000011 :
#3890
0!
0)
#3895
1!
1)
b110000100 :
#3900
0!
0)
#3905
1!
1)
b110000101 :
#3910
0!
0)
#3915
1!
1)
b110000110 :
#3920
0!
0)
#3925
1!
1)
b110000111 :
#3930
0!
0)
#3935
1!
1)
b110001000 :
#3940
0!
0)
#3945
1!
1)
b110001001 :
#3950
0!
0)
#3955
1!
1)
b110001010 :
#3960
0!
0)
#3965
1!
1)
b110001011 :
#3970
0!
0)
#3975
1!
1)
b110001100 :
#3980
0!
0)
#3985
1!
1)
b110001101 :
#3990
0!
0)
#3995
1!
1)
b110001110 :
#4000
0!
0)
#4005
1!
1)
b110001111 :
#4010
0!
0)
#4015
1!
1)
b110010000 :
#4020
0!
0)
#4025
1!
1)
b110010001 :
#4030
0!
0)
#4035
1!
1)
b110010010 :
#4040
0!
0)
#4045
1!
1)
b110010011 :
#4050
0!
0)
#4055
1!
1)
b110010100 :
#4060
0!
0)
#4065
1!
1)
b110010101 :
#4070
0!
0)
#4075
1!
1)
b110010110 :
#4080
0!
0)
#4085
1!
1)
b110010111 :
#4090
0!
0)
#4095
1!
1)
b110011000 :
#4100
0!
0)
#4105
1!
1)
b110011001 :
#4110
0!
0)
#4115
1!
1)
b110011010 :
#4120
0!
0)
#4125
1!
1)
b110011011 :
#4130
0!
0)
#4135
1!
1)
b110011100 :
#4140
0!
0)
#4145
1!
1)
b110011101 :
#4150
0!
0)
#4155
1!
1)
b110011110 :
#4160
0!
0)
#4165
1!
1)
b110011111 :
#4170
0!
0)
#4175
1!
1)
b110100000 :
#4180
0!
0)
#4185
1!
1)
b110100001 :
#4190
0!
0)
#4195
1!
1)
b110100010 :
#4200
0!
0)
#4205
1!
1)
b110100011 :
#4210
0!
0)
#4215
1!
1)
b110100100 :
#4220
0!
0)
#4225
1!
1)
b110100101 :
#4230
0!
0)
#4235
1!
1)
b110100110 :
#4240
0!
0)
#4245
1!
1)
b110100111 :
#4250
0!
0)
#4255
1!
1)
b110101000 :
#4260
0!
0)
#4265
1!
1)
b110101001 :
#4270
0!
0)
#4275
1!
1)
b110101010 :
#4280
0!
0)
#4285
1!
1)
b110101011 :
#4290
0!
0)
#4295
1!
1)
b110101100 :
#4300
0!
0)
#4305
1!
1)
b110101101 :
#4310
0!
0)
#4315
1!
1)
b110101110 :
#4320
0!
0)
#4325
1!
1)
b110101111 :
#4330
0!
0)
#4335
1!
1)
b110110000 :
#4340
0!
0)
#4345
1!
1)
b110110001 :
#4350
0!
0)
#4355
1!
1)
b110110010 :
#4360
0!
0)
#4365
1!
1)
b110110011 :
#4370
0!
0)
#4375
1!
1)
b110110100 :
#4380
0!
0)
#4385
1!
1)
b110110101 :
#4390
0!
0)
#4395
1!
1)
b110110110 :
#4400
0!
0)
#4405
1!
1)
b110110111 :
#4410
0!
0)
#4415
1!
1)
b110111000 :
#4420
0!
0)
#4425
1!
1)
b110111001 :
#4430
0!
0)
#4435
1!
1)
b110111010 :
#4440
0!
0)
#4445
1!
1)
b110111011 :
#4450
0!
0)
#4455
1!
1)
b110111100 :
#4460
0!
0)
#4465
1!
1)
b110111101 :
#4470
0!
0)
#4475
1!
1)
b110111110 :
#4480
0!
0)
#4485
1!
1)
b110111111 :
#4490
0!
0)
#4495
1!
1)
b111000000 :
#4500
0!
0)
#4505
1!
1)
b111000001 :
#4510
0!
0)
#4515
1!
1)
b111000010 :
#4520
0!
0)
#4525
1!
1)
b111000011 :
#4530
0!
0)
#4535
1!
1)
b111000100 :
#4540
0!
0)
#4545
1!
1)
b111000101 :
#4550
0!
0)
#4555
1!
1)
b111000110 :
#4560
0!
0)
#4565
1!
1)
b111000111 :
#4570
0!
0)
#4575
1!
1)
b111001000 :
#4580
0!
0)
#4585
1!
1)
b111001001 :
#4590
0!
0)
#4595
1!
1)
b111001010 :
#4600
0!
0)
#4605
1!
1)
b111001011 :
#4610
0!
0)
#4615
1!
1)
b111001100 :
#4620
0!
0)
#4625
1!
1)
b111001101 :
#4630
0!
0)
#4635
1!
1)
b111001110 :
#4640
0!
0)
#4645
1!
1)
b111001111 :
#4650
0!
0)
#4655
1!
1)
b111010000 :
#4660
0!
0)
#4665
1!
1)
b111010001 :
#4670
0!
0)
#4675
1!
1)
b111010010 :
#4680
0!
0)
#4685
1!
1)
b111010011 :
#4690
0!
0)
#4695
1!
1)
b111010100 :
#4700
0!
0)
#4705
1!
1)
b111010101 :
#4710
0!
0)
#4715
1!
1)
b111010110 :
