semester-modules/Hw02/saturate.sv
module saturate (
    input  logic [16:0]         unsigned_err,
    output logic [9:0]          unsigned_err_sat,
    input  logic signed [16:0]  signed_err,
    output logic signed [9:0]   signed_err_sat,
    input  logic signed [10:0]  signed_diff,
    output logic signed [6:0]   signed_diff_sat
);

    // Unsigned saturation: clamp to 10-bit max (0 .. 1023)\
    always_comb begin
        
        // Unsigned saturation: clamp to 10-bit max (0 .. 1023)
        if (unsigned_err > 10'd1023)
            unsigned_err_sat = 10'h3FF;
        else
            unsigned_err_sat = unsigned_err[9:0];

        // Signed saturation: clamp to 10-bit signed range (-512 .. +511)
        if (signed_err > 10'sd511)
            signed_err_sat = 10'sd511;
        else if (signed_err < -10'sd512)
            signed_err_sat = -10'sd512;
        else
            signed_err_sat = signed_err[9:0];

        // Signed difference saturation: clamp to 7-bit signed range (-64 .. +63)
        if (signed_diff > 7'sd63)
            signed_diff_sat = 7'sd63;
        else if (signed_diff < -7'sd64)
            signed_diff_sat = -7'sd64;
        else
            signed_diff_sat = signed_diff[6:0];
            
    end

endmodule

semester-modules/Ex06/saturate_tb.sv
Timara Empower Recovery
Number: 608-571-3866





module saturate_tb;

    // Inputs
    reg [16:0] unsigned_err;
    reg signed [16:0] signed_err;
    reg signed [10:0] signed_diff;

    // Outputs
    wire [9:0] unsigned_err_sat;
    wire signed [9:0] signed_err_sat;
    wire signed [6:0] signed_diff_sat;

    // loop variable declared at module scope to satisfy older tools that require declarations before statements
    integer i;

    // Instantiate DUT
    saturate iDUT (
        .unsigned_err(unsigned_err),
        .unsigned_err_sat(unsigned_err_sat),
        .signed_err(signed_err),
        .signed_err_sat(signed_err_sat),
        .signed_diff(signed_diff),
        .signed_diff_sat(signed_diff_sat)
    );

    initial begin
        $display("Starting saturate testbench");
        $dumpfile("saturate_tb.vcd");
        $dumpvars(0, saturate_tb);

        // Test vectors: (value, description)
        // Unsigned: 0, small, max in range, just above max
        unsigned_err = 17'd0; signed_err = 17'sd0; signed_diff = 11'sd0; #5;
        $display("u=%0d -> sat=%0d | s=%0d -> sat=%0d | d=%0d -> sat=%0d", unsigned_err, unsigned_err_sat, signed_err, signed_err_sat, signed_diff, signed_diff_sat);

        unsigned_err = 17'd100; signed_err = 17'sd100; signed_diff = 11'sd50; #5;
        $display("u=%0d -> sat=%0d | s=%0d -> sat=%0d | d=%0d -> sat=%0d", unsigned_err, unsigned_err_sat, signed_err, signed_err_sat, signed_diff, signed_diff_sat);

        unsigned_err = 17'd1023; signed_err = 17'sd511; signed_diff = 11'sd63; #5; // at positive limits
        $display("u=%0d -> sat=%0d | s=%0d -> sat=%0d | d=%0d -> sat=%0d", unsigned_err, unsigned_err_sat, signed_err, signed_err_sat, signed_diff, signed_diff_sat);

        unsigned_err = 17'd1024; signed_err = 17'sd512; signed_diff = 11'sd64; #5; // just above positive limits
        $display("u=%0d -> sat=%0d | s=%0d -> sat=%0d | d=%0d -> sat=%0d", unsigned_err, unsigned_err_sat, signed_err, signed_err_sat, signed_diff, signed_diff_sat);

        unsigned_err = 17'd65535; signed_err = -17'sd512; signed_diff = -11'sd64; #5; // large unsigned, at negative signed limits
        $display("u=%0d -> sat=%0d | s=%0d -> sat=%0d | d=%0d -> sat=%0d", unsigned_err, unsigned_err_sat, signed_err, signed_err_sat, signed_diff, signed_diff_sat);

        unsigned_err = 17'd65535; signed_err = -17'sd600; signed_diff = -11'sd100; #5; // below negative limits
        $display("u=%0d -> sat=%0d | s=%0d -> sat=%0d | d=%0d -> sat=%0d", unsigned_err, unsigned_err_sat, signed_err, signed_err_sat, signed_diff, signed_diff_sat);

        // random sweeps quick check
        for (i = -600; i <= 600; i = i + 200) begin
            signed_err = i; signed_diff = i; unsigned_err = i >= 0 ? i : 0; #2;
            $display("s=%0d -> sat=%0d | d=%0d -> sat=%0d", signed_err, signed_err_sat, signed_diff, signed_diff_sat);
        end

        $display("Testbench finished");
        #5 $stop;
    end

endmodule

semester-modules/Ex06/saturate_tb.vcd
$date
	Sun Sep 28 15:54:27 2025
$end
$version
	ModelSim Version 2020.1
$end
$timescale
	1ps
$end

$scope module saturate_tb $end
$var reg 17 ! unsigned_err [16:0] $end
$var reg 17 " signed_err [16:0] $end
$var reg 11 # signed_diff [10:0] $end
$var wire 1 $ unsigned_err_sat [9] $end
$var wire 1 % unsigned_err_sat [8] $end
$var wire 1 & unsigned_err_sat [7] $end
$var wire 1 ' unsigned_err_sat [6] $end
$var wire 1 ( unsigned_err_sat [5] $end
$var wire 1 ) unsigned_err_sat [4] $end
$var wire 1 * unsigned_err_sat [3] $end
$var wire 1 + unsigned_err_sat [2] $end
$var wire 1 , unsigned_err_sat [1] $end
$var wire 1 - unsigned_err_sat [0] $end
$var wire 1 . signed_err_sat [9] $end
$var wire 1 / signed_err_sat [8] $end
$var wire 1 0 signed_err_sat [7] $end
$var wire 1 1 signed_err_sat [6] $end
$var wire 1 2 signed_err_sat [5] $end
$var wire 1 3 signed_err_sat [4] $end
$var wire 1 4 signed_err_sat [3] $end
$var wire 1 5 signed_err_sat [2] $end
$var wire 1 6 signed_err_sat [1] $end
$var wire 1 7 signed_err_sat [0] $end
$var wire 1 8 signed_diff_sat [6] $end
$var wire 1 9 signed_diff_sat [5] $end
$var wire 1 : signed_diff_sat [4] $end
$var wire 1 ; signed_diff_sat [3] $end
$var wire 1 < signed_diff_sat [2] $end
$var wire 1 = signed_diff_sat [1] $end
$var wire 1 > signed_diff_sat [0] $end
$var integer 32 ? i $end

$scope module iDUT $end
$var wire 1 @ unsigned_err [16] $end
$var wire 1 A unsigned_err [15] $end
$var wire 1 B unsigned_err [14] $end
$var wire 1 C unsigned_err [13] $end
$var wire 1 D unsigned_err [12] $end
$var wire 1 E unsigned_err [11] $end
$var wire 1 F unsigned_err [10] $end
$var wire 1 G unsigned_err [9] $end
$var wire 1 H unsigned_err [8] $end
$var wire 1 I unsigned_err [7] $end
$var wire 1 J unsigned_err [6] $end
$var wire 1 K unsigned_err [5] $end
$var wire 1 L unsigned_err [4] $end
$var wire 1 M unsigned_err [3] $end
$var wire 1 N unsigned_err [2] $end
$var wire 1 O unsigned_err [1] $end
$var wire 1 P unsigned_err [0] $end
$var reg 10 Q unsigned_err_sat [9:0] $end
$var wire 1 R signed_err [16] $end
$var wire 1 S signed_err [15] $end
$var wire 1 T signed_err [14] $end
$var wire 1 U signed_err [13] $end
$var wire 1 V signed_err [12] $end
$var wire 1 W signed_err [11] $end
$var wire 1 X signed_err [10] $end
$var wire 1 Y signed_err [9] $end
$var wire 1 Z signed_err [8] $end
$var wire 1 [ signed_err [7] $end
$var wire 1 \ signed_err [6] $end
$var wire 1 ] signed_err [5] $end
$var wire 1 ^ signed_err [4] $end
$var wire 1 _ signed_err [3] $end
$var wire 1 ` signed_err [2] $end
$var wire 1 a signed_err [1] $end
$var wire 1 b signed_err [0] $end
$var reg 10 c signed_err_sat [9:0] $end
$var wire 1 d signed_diff [10] $end
$var wire 1 e signed_diff [9] $end
$var wire 1 f signed_diff [8] $end
$var wire 1 g signed_diff [7] $end
$var wire 1 h signed_diff [6] $end
$var wire 1 i signed_diff [5] $end
$var wire 1 j signed_diff [4] $end
$var wire 1 k signed_diff [3] $end
$var wire 1 l signed_diff [2] $end
$var wire 1 m signed_diff [1] $end
$var wire 1 n signed_diff [0] $end
$var reg 7 o signed_diff_sat [6:0] $end
$upscope $end
$upscope $end
$enddefinitions $end
#0
$dumpvars
b0 !
b0 "
b0 #
b0 Q
b1000000000 c
b1000000 o
bx ?
0-
0,
0+
0*
0)
0(
0'
0&
0%
0$
07
06
05
04
03
02
01
00
0/
1.
0>
0=
0<
0;
0:
09
18
0P
0O
0N
0M
0L
0K
0J
0I
0H
0G
0F
0E
0D
0C
0B
0A
0@
0b
0a
0`
0_
0^
0]
0\
0[
0Z
0Y
0X
0W
0V
0U
0T
0S
0R
0n
0m
0l
0k
0j
0i
0h
0g
0f
0e
0d
$end
#5
b1100100 !
b1100100 "
b110010 #
1m
1j
1i
1`
1]
1\
1N
1K
1J
b1100100 Q
1+
1(
1'
#10
b1111111111 !
b111111111 "
b111111 #
1n
1l
1k
1b
1a
1_
1^
1[
1Z
1P
1O
1M
1L
1I
1H
1G
b1111111111 Q
1-
1,
1*
1)
1&
1%
1$
#15
b10000000000 !
b1000000000 "
b1000000 #
0n
0m
0l
0k
0j
0i
1h
0b
0a
0`
0_
0^
0]
0\
0[
0Z
1Y
0P
0O
0N
0M
0L
0K
0J
0I
0H
0G
1F
b111111111 c
b111111 o
1>
1=
1<
1;
1:
19
08
17
16
15
14
13
12
11
10
1/
0.
#20
b1111111111111111 !
b11111111000000000 "
b11111000000 #
1g
1f
1e
1d
1X
1W
1V
1U
1T
1S
1R
1P
1O
1N
1M
1L
1K
1J
1I
1H
1G
1E
1D
1C
1B
1A
b1000000000 c
b1000000 o
0>
0=
0<
0;
0:
09
18
07
06
05
04
03
02
01
00
0/
1.
#25
b11111110110101000 "
b11110011100 #
1l
1k
1j
0h
1_
1]
1[
1Z
0Y
#30
b11111111111111111111110110101000 ?
b10110101000 #
b0 !
0P
0O
0N
0M
0L
0K
0J
0I
0H
0G
0F
0E
0D
0C
0B
0A
0l
0j
1i
0e
b0 Q
0-
0,
0+
0*
0)
0(
0'
0&
0%
0$
#32
b11111111111111111111111001110000 ?
b11111111001110000 "
b11001110000 #
0k
1j
1h
0g
0f
1e
0_
1^
1\
0[
0Z
1Y
#34
b11111111111111111111111100111000 ?
b11111111100111000 "
b11100111000 #
1k
0h
1f
1_
0\
1Z
#36
b0 ?
b0 "
b0 #
0k
0j
0i
0f
0e
0d
0_
0^
0]
0Z
0Y
0X
0W
0V
0U
0T
0S
0R
#38
b11001000 ?
b11001000 "
b11001000 #
b11001000 !
1M
1J
1I
1k
1h
1g
1_
1\
1[
b11001000 Q
b111111 o
1>
1=
1<
1;
1:
19
08
1*
1'
1&
#40
b110010000 ?
b110010000 "
b110010000 #
b110010000 !
0M
1L
0J
1H
0k
1j
0h
1f
0_
1^
0\
1Z
b110010000 Q
0*
1)
0'
1%
#42
b1001011000 ?
b1001011000 "
b1001011000 #
b1001011000 !
1M
1J
0I
0H
1G
1k
1h
0g
0f
1e
1_
1\
0[
0Z
1Y
b1001011000 Q
b111111111 c
17
16
15
14
13
12
11
10
1/
0.
1*
1'
0&
0%
1$
#44
b1100100000 ?
